ec2_dev_machine/__init__.py
ec2_dev_machine/cdk/ec2_stack.py
ec2_dev_machine/config.py
ec2_dev_machine/core.py
ec2_dev_machine/user_data/setup.sh.template
ec2_dev_machine/user_data/user_data.py
ec2_dev_machine-0.1.1.dist-info/LICENSE
ec2_dev_machine-0.1.1.dist-info/METADATA
ec2_dev_machine-0.1.1.dist-info/WHEEL
ec2_dev_machine-0.1.1.dist-info/RECORD
